README.txt
setup.py
bar4py/__init__.py
bar4py/cameraparameters.py
bar4py/command.py
bar4py/debugtools.py
bar4py/dictionary.py
bar4py/marker.py
bar4py/markerdetector.py
bar4py/shortfuncs.py
bar4py/version.py
bar4py/web.py
bar4py.egg-info/PKG-INFO
bar4py.egg-info/SOURCES.txt
bar4py.egg-info/dependency_links.txt
bar4py.egg-info/entry_points.txt
bar4py.egg-info/requires.txt
bar4py.egg-info/top_level.txt
bar4py/resources/webplayer.py
bar4py/resources/static/animate/animate.js
bar4py/resources/static/camera/camera_640x480.json
bar4py/resources/static/dictionary/dictionary.json
bar4py/resources/static/marker/701.jpg
bar4py/resources/static/model/rocket.mtl
bar4py/resources/static/model/rocket.obj
bar4py/resources/static/model/rocket.png
bar4py/static/js/MTLLoader.js
bar4py/static/js/OBJLoader.js
bar4py/static/js/barviews.js
bar4py/static/js/three.min.js
bar4py/templates/index.tpl