Metadata-Version: 1.0
Name: bar4py
Version: 0.1.2.0
Summary: Augmented reality lib for Python3
Home-page: https://bxtkezhan.github.io/BAR4Py
Author: bxtkezhan-kk
Author-email: bxtkezhan@qq.com
License: MIT License
Keywords: AR OpenCV
Platform: UNKNOWN
